simple_googesheet_interface/__init__.py
simple_googlesheet_interface-0.1.0.data/data/requirements.txt
simple_googlesheet_interface-0.1.0.dist-info/licenses/LICENSE
simple_googlesheet_interface-0.1.0.dist-info/METADATA
simple_googlesheet_interface-0.1.0.dist-info/WHEEL
simple_googlesheet_interface-0.1.0.dist-info/top_level.txt
simple_googlesheet_interface-0.1.0.dist-info/RECORD
